citeproc/__init__.py
citeproc/_version.py
citeproc/frontend.py
citeproc/model.py
citeproc/string.py
citeproc/types.py
citeproc/data/locales/locales-af-ZA.xml
citeproc/data/locales/locales-ar.xml
citeproc/data/locales/locales-bg-BG.xml
citeproc/data/locales/locales-ca-AD.xml
citeproc/data/locales/locales-cs-CZ.xml
citeproc/data/locales/locales-cy-GB.xml
citeproc/data/locales/locales-da-DK.xml
citeproc/data/locales/locales-de-AT.xml
citeproc/data/locales/locales-de-CH.xml
citeproc/data/locales/locales-de-DE.xml
citeproc/data/locales/locales-el-GR.xml
citeproc/data/locales/locales-en-GB.xml
citeproc/data/locales/locales-en-US.xml
citeproc/data/locales/locales-es-CL.xml
citeproc/data/locales/locales-es-ES.xml
citeproc/data/locales/locales-es-MX.xml
citeproc/data/locales/locales-et-EE.xml
citeproc/data/locales/locales-eu.xml
citeproc/data/locales/locales-fa-IR.xml
citeproc/data/locales/locales-fi-FI.xml
citeproc/data/locales/locales-fr-CA.xml
citeproc/data/locales/locales-fr-FR.xml
citeproc/data/locales/locales-he-IL.xml
citeproc/data/locales/locales-hi-IN.xml
citeproc/data/locales/locales-hr-HR.xml
citeproc/data/locales/locales-hu-HU.xml
citeproc/data/locales/locales-id-ID.xml
citeproc/data/locales/locales-is-IS.xml
citeproc/data/locales/locales-it-IT.xml
citeproc/data/locales/locales-ja-JP.xml
citeproc/data/locales/locales-km-KH.xml
citeproc/data/locales/locales-ko-KR.xml
citeproc/data/locales/locales-la.xml
citeproc/data/locales/locales-lt-LT.xml
citeproc/data/locales/locales-lv-LV.xml
citeproc/data/locales/locales-mn-MN.xml
citeproc/data/locales/locales-nb-NO.xml
citeproc/data/locales/locales-nl-NL.xml
citeproc/data/locales/locales-nn-NO.xml
citeproc/data/locales/locales-pl-PL.xml
citeproc/data/locales/locales-pt-BR.xml
citeproc/data/locales/locales-pt-PT.xml
citeproc/data/locales/locales-ro-RO.xml
citeproc/data/locales/locales-ru-RU.xml
citeproc/data/locales/locales-sk-SK.xml
citeproc/data/locales/locales-sl-SI.xml
citeproc/data/locales/locales-sr-RS.xml
citeproc_py-0.8.3.dist-info/licenses/LICENSE
citeproc_py-0.8.3.dist-info/METADATA
citeproc_py-0.8.3.dist-info/WHEEL
citeproc_py-0.8.3.dist-info/top_level.txt
citeproc_py-0.8.3.dist-info/RECORD
